nntime/__init__.py
nntime/timing.py
nntime-0.1.1.dist-info/LICENSE
nntime-0.1.1.dist-info/METADATA
nntime-0.1.1.dist-info/WHEEL
nntime-0.1.1.dist-info/top_level.txt
nntime-0.1.1.dist-info/RECORD
