Metadata-Version: 2.1
Name: nntime
Version: 0.1.1
Summary: Timing utilities for deep learning modules in PyTorch
Home-page: https://github.com/mtli/nntime
Author: Mengtian (Martin) Li
Author-email: martinli.work@gmail.com
License: MIT
Keywords: deep learning pytorch timing profiling
Platform: UNKNOWN
Classifier: Development Status :: 4 - Beta
Classifier: Intended Audience :: Science/Research
Classifier: Topic :: Scientific/Engineering :: Artificial Intelligence
Classifier: License :: OSI Approved :: MIT License
Classifier: Programming Language :: Python :: 3
Requires-Python: >=3
Requires-Dist: numpy
